{
    "web_url": "http://www.nytimes.com/reuters/2016/12/19/sports/autoracing/19reuters-motor-f1-mclaren-capito.html",
    "snippet": "McLaren Racing chief executive Jost Capito is set to follow Ron Dennis out of the Formula One team, the BBC and Autosport.com reported on Monday....",
    "lead_paragraph": "McLaren Racing chief executive Jost Capito is set to follow Ron Dennis out of the Formula One team, the BBC and Autosport.com reported on Monday.",
    "abstract": null,
    "print_page": null,
    "blog": [],
    "source": "Reuters",
    "multimedia": [],
    "headline": {
        "main": "Chief Executive Capito Set to Leave McLaren: Reports",
        "print_headline": "Chief Executive Capito Set to Leave McLaren: Reports"
    },
    "keywords": [],
    "pub_date": "2016-12-20T00:57:28+0000",
    "document_type": "article",
    "news_desk": null,
    "section_name": "Sports",
    "subsection_name": "Auto Racing",
    "byline": {
        "person": [],
        "original": "By REUTERS",
        "organization": "REUTERS"
    },
    "type_of_material": "News",
    "_id": "585881fc95d0e03926076e02",
    "word_count": "137",
    "slideshow_credits": null
}