{
    "web_url": "http://www.nytimes.com/reuters/2016/12/17/sports/soccer/17reuters-soccer-england-swa-bradley.html",
    "snippet": "Swansea City manager Bob Bradley wants his struggling side to stay united and stop digging holes for themselves after Saturday's 3-0 loss at Middlesbrough left the Welsh side second from bottom in the Premier League....",
    "lead_paragraph": "Swansea City manager Bob Bradley wants his struggling side to stay united and stop digging holes for themselves after Saturday's 3-0 loss at Middlesbrough left the Welsh side second from bottom in the Premier League.",
    "abstract": null,
    "print_page": null,
    "blog": [],
    "source": "Reuters",
    "multimedia": [],
    "headline": {
        "main": "Bradley Demands Unity in Swansea Fight Against the Drop",
        "print_headline": "Bradley Demands Unity in Swansea Fight Against the Drop"
    },
    "keywords": [],
    "pub_date": "2016-12-18T00:18:28+0000",
    "document_type": "article",
    "news_desk": null,
    "section_name": "Sports",
    "subsection_name": "Soccer",
    "byline": {
        "person": [],
        "original": "By REUTERS",
        "organization": "REUTERS"
    },
    "type_of_material": "News",
    "_id": "5855d5da95d0e0392607699f",
    "word_count": "367",
    "slideshow_credits": null
}