{
    "web_url": "http://www.nytimes.com/reuters/2016/12/30/sports/cycling/30reuters-cycling-swiss-kuebler.html",
    "snippet": "Ferdinand \"Ferdy\" Kuebler, the first Swiss cyclist to win the Tour de France, died on Thursday in a Zurich hospital at the age of 97 following a brief illness, the Swiss Cycling federation said on its website....",
    "lead_paragraph": "Ferdinand \"Ferdy\" Kuebler, the first Swiss cyclist to win the Tour de France, died on Thursday in a Zurich hospital at the age of 97 following a brief illness, the Swiss Cycling federation said on its website.",
    "abstract": null,
    "print_page": null,
    "blog": [],
    "source": "Reuters",
    "multimedia": [],
    "headline": {
        "main": "Kuebler, First Swiss Tour De France Champion, Dies at 97",
        "print_headline": "Kuebler, First Swiss Tour De France Champion, Dies at 97"
    },
    "keywords": [],
    "pub_date": "2016-12-30T11:57:30+0000",
    "document_type": "article",
    "news_desk": null,
    "section_name": "Sports",
    "subsection_name": "Cycling",
    "byline": {
        "person": [],
        "original": "By REUTERS",
        "organization": "REUTERS"
    },
    "type_of_material": "News",
    "_id": "58664baf95d0e0392607854c",
    "word_count": "141",
    "slideshow_credits": null
}