{
    "web_url": "https://www.nytimes.com/2000/05/07/us/national-news-briefs-california-indians-win-final-casino-approval.html",
    "snippet": "California Indian tribes have received federal approval of gambling agreements with Gov. Gray Davis, clearing the final hurdle to legalizing their casinos.    The gambling compacts with about 60 tribes were approved on Friday by Kevin Gover, the I...",
    "lead_paragraph": "California Indian tribes have received federal approval of gambling agreements with Gov. Gray Davis, clearing the final hurdle to legalizing their casinos. The gambling compacts with about 60 tribes were approved on Friday by Kevin Gover, the Interior Department's assistant secretary of Indian affairs. The agreement ended a long fight by the tribes to run casinos.",
    "abstract": "California Indian tribes receive federal approval of gambling agreements with Gov Gray Davis, clearing final hurdle to legalizing their casinos (S)",
    "print_page": "38",
    "blog": [],
    "source": "AP",
    "multimedia": [],
    "headline": {
        "main": "National News Briefs; California Indians Win Final Casino Approval"
    },
    "keywords": [
        {
            "name": "persons",
            "value": "DAVIS, GRAY"
        },
        {
            "name": "glocations",
            "value": "CALIFORNIA"
        },
        {
            "name": "subject",
            "value": "INDIANS, AMERICAN"
        },
        {
            "name": "subject",
            "value": "GAMBLING"
        },
        {
            "name": "subject",
            "value": "CASINOS"
        }
    ],
    "pub_date": "2000-05-07T00:00:00Z",
    "document_type": "article",
    "news_desk": "National Desk",
    "section_name": null,
    "subsection_name": null,
    "byline": null,
    "type_of_material": "News",
    "_id": "4fd216818eb7c8105d790b6e",
    "word_count": "97",
    "slideshow_credits": null
}