{
    "web_url": "https://www.nytimes.com/1993/02/25/us/california-school-chief-is-placed-on-probation.html",
    "snippet": "The California Superintendent of Public Instruction was sentenced today to four years' probation for violating the state's conflict-of-interest law and was ordered to repay more than $330,000 to the state.   The Superintendent, Bill Honig, was con...",
    "lead_paragraph": "The California Superintendent of Public Instruction was sentenced today to four years' probation for violating the state's conflict-of-interest law and was ordered to repay more than $330,000 to the state. The Superintendent, Bill Honig, was convicted on Jan. 29 of four felony counts for entering the state into contracts that benefited the Quality Education Project, a not-for-profit organization headed by his wife, Nancy.",
    "abstract": null,
    "print_page": "7",
    "blog": [],
    "source": "The New York Times",
    "multimedia": [],
    "headline": {
        "main": "California School Chief Is Placed on Probation"
    },
    "keywords": [
        {
            "name": "persons",
            "value": "HONIG, BILL"
        },
        {
            "name": "glocations",
            "value": "CALIFORNIA"
        },
        {
            "name": "subject",
            "value": "PROBATION AND PAROLE"
        },
        {
            "name": "subject",
            "value": "EDUCATION AND SCHOOLS"
        },
        {
            "name": "subject",
            "value": "SENTENCES (CRIMINAL)"
        },
        {
            "name": "subject",
            "value": "ETHICS"
        }
    ],
    "pub_date": "1993-02-25T00:00:00Z",
    "document_type": "article",
    "news_desk": "National Desk",
    "section_name": "Education; U.S.",
    "subsection_name": null,
    "byline": null,
    "type_of_material": "News",
    "_id": "4fd1e5b08eb7c8105d7311fd",
    "word_count": 128,
    "slideshow_credits": null
}