{
    "web_url": "http://www.nytimes.com/aponline/2016/12/29/sports/ncaabasketball/ap-bkc-father-son-milestone.html",
    "snippet": "Xavier Rathan-Mayes became the 46th Florida State player to reach 1,000 career points on Wednesday. But when his layup with 15:47 remaining in the first half against Wake Forest put him at 1,001, it resulted in another, rarer milestone....",
    "lead_paragraph": "Xavier Rathan-Mayes became the 46th Florida State player to reach 1,000 career points on Wednesday. But when his layup with 15:47 remaining in the first half against Wake Forest put him at 1,001, it resulted in another, rarer milestone.",
    "abstract": null,
    "print_page": null,
    "blog": [],
    "source": "AP",
    "multimedia": [],
    "headline": {
        "main": "FSU Father-Son Duo First in ACC to Reach 1,000-Point Club",
        "print_headline": "FSU Father-Son Duo First in ACC to Reach 1,000-Point Club"
    },
    "keywords": [],
    "pub_date": "2016-12-29T05:45:35+0000",
    "document_type": "article",
    "news_desk": null,
    "section_name": "Sports",
    "subsection_name": "College Basketball",
    "byline": {
        "person": [],
        "original": "By THE ASSOCIATED PRESS",
        "organization": "THE ASSOCIATED PRESS"
    },
    "type_of_material": "News",
    "_id": "5864a32c95d0e0392607823b",
    "word_count": "510",
    "slideshow_credits": null
}