{
    "web_url": "https://www.nytimes.com/1992/05/24/us/california-assault-weapons-ban-is-upheld.html",
    "snippet": "California's ban on the sale of semiautomatic assault weapons, enacted after five children were shot to death in a Stockton schoolyard in 1989, was upheld Friday by a Federal appeals court.    The ruling, issued by a unanimous three-judge panel of...",
    "lead_paragraph": "California's ban on the sale of semiautomatic assault weapons, enacted after five children were shot to death in a Stockton schoolyard in 1989, was upheld Friday by a Federal appeals court. The ruling, issued by a unanimous three-judge panel of the United States Court of Appeals for the Ninth Circuit, rejected arguments by the National Rifle Association that the law, the first of its kind in the nation, violates the constitutional right to bear arms.",
    "abstract": null,
    "print_page": "23",
    "blog": [],
    "source": "AP",
    "multimedia": [],
    "headline": {
        "main": "California Assault-Weapons Ban Is Upheld"
    },
    "keywords": [
        {
            "name": "glocations",
            "value": "CALIFORNIA"
        },
        {
            "name": "subject",
            "value": "GUN CONTROL"
        },
        {
            "name": "subject",
            "value": "LAW AND LEGISLATION"
        },
        {
            "name": "subject",
            "value": "FIREARMS"
        },
        {
            "name": "subject",
            "value": "DECISIONS AND VERDICTS"
        }
    ],
    "pub_date": "1992-05-24T00:00:00Z",
    "document_type": "article",
    "news_desk": "National Desk",
    "section_name": null,
    "subsection_name": null,
    "byline": null,
    "type_of_material": "News",
    "_id": "4fd1db418eb7c8105d71bc2b",
    "word_count": 208,
    "slideshow_credits": null
}