{
    "web_url": "https://www.nytimes.com/1998/06/01/opinion/l-shareholders-can-sell-184160.html",
    "snippet": "To the Editor:    Re ''Treating Shareholders Like Workers'' (editorial, May 29): Regarding California's Proposition 226, I do not understand how you can equate a shareholder in a corporation with a worker who as a condition of employment must pay ...",
    "lead_paragraph": "To the Editor: Re ''Treating Shareholders Like Workers'' (editorial, May 29): Regarding California's Proposition 226, I do not understand how you can equate a shareholder in a corporation with a worker who as a condition of employment must pay union dues. A shareholder can sell his stake in a company that supports political entities he finds offensive.",
    "abstract": "John McCaffrey letter comments on May 29 editorial regarding California's Proposition 226, which seeks to reaffirm right of union members to refund of portion of dues not used for collective bargaining (S)",
    "print_page": "14",
    "blog": [],
    "source": "The New York Times",
    "multimedia": [],
    "headline": {
        "main": "Shareholders Can Sell"
    },
    "keywords": [
        {
            "name": "glocations",
            "value": "CALIFORNIA"
        },
        {
            "name": "subject",
            "value": "LABOR"
        },
        {
            "name": "subject",
            "value": "EDITORIALS"
        },
        {
            "name": "subject",
            "value": "ELECTION ISSUES"
        },
        {
            "name": "subject",
            "value": "REFERENDUMS"
        }
    ],
    "pub_date": "1998-06-01T00:00:00Z",
    "document_type": "article",
    "news_desk": "Editorial Desk",
    "section_name": "Opinion",
    "subsection_name": null,
    "byline": null,
    "type_of_material": "Letter",
    "_id": "4fd1eafd8eb7c8105d73b3aa",
    "word_count": 108,
    "slideshow_credits": null
}