{
    "web_url": "http://www.nytimes.com/2016/11/09/us/politics/rosanell-eaton-voting-rights-north-carolina.html",
    "snippet": "Since registering to vote when she was 19, Rosanell Eaton, a lifelong North Carolina resident, has navigated around efforts to disenfranchise and intimidate her....",
    "lead_paragraph": "Since registering to vote when she was 19, Rosanell Eaton, a lifelong North Carolina resident, has navigated around efforts to disenfranchise and intimidate her.",
    "abstract": null,
    "print_page": null,
    "blog": [],
    "source": "The New York Times",
    "multimedia": [],
    "headline": {
        "main": "At 95, Continuing the Fight for the Right to Vote in North Carolina"
    },
    "keywords": [
        {
            "rank": "1",
            "is_major": "N",
            "name": "subject",
            "value": "Blacks"
        },
        {
            "rank": "2",
            "is_major": "N",
            "name": "subject",
            "value": "Elections"
        },
        {
            "rank": "3",
            "is_major": "N",
            "name": "subject",
            "value": "Presidential Election of 2016"
        },
        {
            "rank": "4",
            "is_major": "N",
            "name": "persons",
            "value": "Eaton, Rosanell (1921- )"
        }
    ],
    "pub_date": "2016-11-09T03:10:03Z",
    "document_type": "article",
    "news_desk": "Express",
    "section_name": "U.S.",
    "subsection_name": "Politics",
    "byline": {
        "person": [],
        "original": "By THE NEW YORK TIMES",
        "organization": "THE NEW YORK TIMES"
    },
    "type_of_material": "News",
    "_id": "582293927c459f6a5fcccf58",
    "word_count": "183",
    "slideshow_credits": null
}